CHANGES.txt
LICENSE
MANIFEST.in
README.rst
setup.py
bamfordlab/__init__.py
bamfordlab/bibtex.py
bamfordlab/constants.py
bamfordlab/protocols.conf
bamfordlab/wizards.py
bamfordlab/protocols/__init__.py
bamfordlab/protocols/protocol_ethan_picking.py
bamfordlab/tests/__init__.py
bamfordlab/tests/test_protocol_ethan.py
scipion_em_bamfordlab.egg-info/PKG-INFO
scipion_em_bamfordlab.egg-info/SOURCES.txt
scipion_em_bamfordlab.egg-info/dependency_links.txt
scipion_em_bamfordlab.egg-info/entry_points.txt
scipion_em_bamfordlab.egg-info/requires.txt
scipion_em_bamfordlab.egg-info/top_level.txt