Metadata-Version: 1.1
Name: scipion-em-bamfordlab
Version: 3.0.0
Summary: Plugin to use Bamfordlab programs within the Scipion framework
Home-page: https://github.com/scipion-em/scipion-em-bamfordlab
Author: J.M. De la Rosa Trevin
Author-email: delarosatrevin@scilifelab.se
License: UNKNOWN
Keywords: scipion electron-microscopy cryo-em structural-biology image-processing scipion-3.0
Platform: UNKNOWN
Classifier: Development Status :: 4 - Beta
Classifier: License :: OSI Approved :: GNU General Public License v3 (GPLv3)
Classifier: Programming Language :: Python :: 3
